slightly_better_dicts/__init__.py
slightly_better_dicts/better_dict.py
slightly_better_dicts/fn.py
slightly_better_dicts/py.typed
slightly_better_dicts-0.1.0.dist-info/WHEEL
slightly_better_dicts-0.1.0.dist-info/METADATA
slightly_better_dicts-0.1.0.dist-info/RECORD
