Metadata-Version: 2.3
Name: slightly-better-dicts
Version: 0.1.0
Summary: A Python library that provides some classes and functions that add quality of life improvements to the standard library's `dict`
Author: Matt Hale
Author-email: Matt Hale <matthew.hale@protonmail.com>
Requires-Python: >=3.13
